LICENSE
MANIFEST.in
README.md
pyproject.toml
rxxxt/__init__.py
rxxxt/app.py
rxxxt/asgi.py
rxxxt/component.py
rxxxt/elements.py
rxxxt/execution.py
rxxxt/helpers.py
rxxxt/node.py
rxxxt/page.py
rxxxt/py.typed
rxxxt/renderer.py
rxxxt/router.py
rxxxt/session.py
rxxxt/state.py
rxxxt.egg-info/PKG-INFO
rxxxt.egg-info/SOURCES.txt
rxxxt.egg-info/dependency_links.txt
rxxxt.egg-info/requires.txt
rxxxt.egg-info/top_level.txt
rxxxt/assets/.gitignore
rxxxt/assets/main.js
tests/test_app.py
tests/test_asgi.py
tests/test_components.py
tests/test_elements.py
tests/test_jwt.py
tests/test_other.py
tests/test_router.py
tests/test_session.py