Metadata-Version: 2.4
Name: rxxxt
Version: 0.4.1
Summary: Server side rendered, reactive web applications in python.
Author: leopf
License: MIT License
Project-URL: Homepage, https://leopf.github.io/rxxxt/
Project-URL: Repository, https://github.com/leopf/rxxxt
License-File: LICENSE
Requires-Dist: pydantic>=2.9.0
Provides-Extra: dev
Requires-Dist: ruff; extra == "dev"
Requires-Dist: uvicorn[standard]; extra == "dev"
Provides-Extra: testing
Requires-Dist: pyjwt; extra == "testing"
Requires-Dist: httpx; extra == "testing"
Requires-Dist: httpx-ws==0.8.0; extra == "testing"
Provides-Extra: docs
Requires-Dist: mkdocs; extra == "docs"
Requires-Dist: mkdocstrings[python]; extra == "docs"
Requires-Dist: mkdocs-material; extra == "docs"
Dynamic: license-file
